gc_monitor/__init__.py
gc_monitor/__main__.py
gc_monitor/blunders.py
gc_monitor/callback.py
gc_monitor/cli.py
gc_monitor/codegen.py
gc_monitor/flamegraph.py
gc_monitor/logging.py
gc_monitor/monitor.py
gc_monitor/processing.py
gc_monitor/prompts.py
gc_monitor/stats.py
gc_monitor/udp_emitter.py
gc_monitor/utils.py
gc_monitor/dashboard/server.py
gc_monitor/dashboard/static/index.html
gc_monitor/dashboard/static/css/style.css
gc_monitor/dashboard/static/js/app.js
gc_monitor/prompts/__init__.py
gc_monitor/prompts/builder.py
gc_monitor/prompts/context.py
gc_monitor/prompts/detector.py
gc_monitor/prompts/templates/__init__.py
gc_monitor/prompts/templates/headers.py
gc_monitor/prompts/templates/issues.py
gc_monitor/prompts/templates/solutions.py
gc_monitor/prompts/templates/validation.py
pygcprofiler-0.4.1.dist-info/METADATA
pygcprofiler-0.4.1.dist-info/WHEEL
pygcprofiler-0.4.1.dist-info/entry_points.txt
pygcprofiler-0.4.1.dist-info/licenses/LICENSE
pygcprofiler-0.4.1.dist-info/RECORD
