Metadata-Version: 2.4
Name: pygcprofiler
Version: 0.4.1
Summary: See Python's garbage collector in action without getting in its way. Zero-overhead GC monitoring for production applications.
Project-URL: Homepage, https://github.com/IntegerAlex/pygcprofiler
Project-URL: Documentation, https://github.com/IntegerAlex/pygcprofiler#readme
Project-URL: Repository, https://github.com/IntegerAlex/pygcprofiler.git
Project-URL: Issues, https://github.com/IntegerAlex/pygcprofiler/issues
Project-URL: Changelog, https://github.com/IntegerAlex/pygcprofiler/blob/main/CHANGELOG.md
Author-email: Akshat Kotpalliwar <akshatkot@gmail.com>
Maintainer-email: Akshat Kotpalliwar <akshatkot@gmail.com>
License-Expression: LGPL-2.1-only
License-File: LICENSE
Keywords: debugging,garbage-collection,gc,memory,monitoring,observability,performance,profiling
Classifier: Development Status :: 4 - Beta
Classifier: Environment :: Console
Classifier: Intended Audience :: Developers
Classifier: License :: OSI Approved :: GNU Lesser General Public License v2 or later (LGPLv2+)
Classifier: Operating System :: OS Independent
Classifier: Programming Language :: Python :: 3
Classifier: Programming Language :: Python :: 3.10
Classifier: Programming Language :: Python :: 3.11
Classifier: Programming Language :: Python :: 3.12
Classifier: Programming Language :: Python :: 3.13
Classifier: Topic :: Software Development :: Debuggers
Classifier: Topic :: Software Development :: Testing
Classifier: Topic :: System :: Monitoring
Classifier: Typing :: Typed
Requires-Python: >=3.10
Requires-Dist: psutil>=5.9.0
Requires-Dist: typing-extensions>=4.8.0
Provides-Extra: dashboard
Requires-Dist: fastapi>=0.104.0; extra == 'dashboard'
Requires-Dist: httpx>=0.25.0; extra == 'dashboard'
Requires-Dist: pytest-asyncio>=0.21.0; extra == 'dashboard'
Requires-Dist: uvicorn[standard]>=0.24.0; extra == 'dashboard'
Provides-Extra: dev
Requires-Dist: mypy>=1.10.0; extra == 'dev'
Requires-Dist: pytest-cov>=4.0.0; extra == 'dev'
Requires-Dist: pytest>=8.0.0; extra == 'dev'
Requires-Dist: ruff>=0.4.0; extra == 'dev'
Requires-Dist: typing-extensions>=4.8.0; extra == 'dev'
